<?xml version="1.0" encoding="utf-8" ?>
<RegularExpression>
  <RegularExpressions>
    <ID>1</ID>
    <Description>Email Address</Description>
    <Expression>^[\w-\.]+@([\w-]+\.)+[\w-]{2,4}$</Expression>
    <NamesToMatch>Email,EmailAddress,EmailAddr</NamesToMatch>
    <Message>The format for {0} is invalid</Message>
  </RegularExpressions>
  <RegularExpressions>
    <ID>2</ID>
    <Description>WWW Address</Description>
    <Expression>^([a-zA-Z0-9]([a-zA-Z0-9\-]{0,61}[a-zA-Z0-9])?\.)+[a-zA-Z]{2,6}$</Expression>
    <NamesToMatch>URL</NamesToMatch>
    <Message>The format for {0} is invalid</Message>
  </RegularExpressions>
  <RegularExpressions>
    <ID>3</ID>
    <Description>North American Telephone Number</Description>
    <Expression>^\(?(?&lt;AreaCode&gt;[2-9]\d{2})(\)?)(-|.|\s)?(?&lt;Prefix&gt;[1-9]\d{2})(-|.|\s)?(?&lt;Suffix&gt;\d{4})$</Expression>
    <NamesToMatch>Phone,Telephone,PhoneNumber</NamesToMatch>
    <Message>The format for {0} is invalid</Message>
  </RegularExpressions>
  <RegularExpressions>
    <ID>4</ID>
    <Description>North American Zip Code (Zip and Zip+4)</Description>
    <Expression>(^(?!0{5})(\d{5})(?!-?0{4})(-?\d{4})?$)</Expression>
    <NamesToMatch>Zip,ZipCode,PostalCode</NamesToMatch>
    <Message>The format for {0} is invalid</Message>
  </RegularExpressions>
  <RegularExpressions>
    <ID>5</ID>
    <Description>UK Postal Codes</Description>
    <Expression>(((^[BEGLMNS][1-9]\d?) | (^W[2-9] ) | ( ^( A[BL] | B[ABDHLNRST] | C[ABFHMORTVW] | D[ADEGHLNTY] | E[HNX] | F[KY] | G[LUY] | H[ADGPRSUX] | I[GMPV] | JE | K[ATWY] | L[ADELNSU] | M[EKL] | N[EGNPRW] | O[LX] | P[AEHLOR] | R[GHM] | S[AEGKL-PRSTWY] | T[ADFNQRSW] | UB | W[ADFNRSV] | YO | ZE ) \d\d?) | (^W1[A-HJKSTUW0-9]) | (( (^WC[1-2]) | (^EC[1-4]) | (^SW1) ) [ABEHMNPRVWXY] ) ) (\s*)? ([0-9][ABD-HJLNP-UW-Z]{2})) | (^GIR\s?0AA)</Expression>
    <NamesToMatch>PostalCode</NamesToMatch>
    <Message>The format for {0} is invalid</Message>
  </RegularExpressions>
  <RegularExpressions>
    <ID>6</ID>
    <Description>UK Phone Numbers</Description>
    <Expression>^(((\+44\s?\d{4}|\(?0\d{4}\)?)\s?\d{3}\s?\d{3})|((\+44\s?\d{3}|\(?0\d{3}\)?)\s?\d{3}\s?\d{4})|((\+44\s?\d{2}|\(?0\d{2}\)?)\s?\d{4}\s?\d{4}))(\s?\#(\d{4}|\d{3}))?$</Expression>
    <NamesToMatch>Zip,ZipCode,PostalCode</NamesToMatch>
    <Message>The format for {0} is invalid</Message>
  </RegularExpressions>
  <RegularExpressions>
    <ID>7</ID>
    <Description>TCP/IP Addresses</Description>
    <Expression>^((\d|\d\d|[0-1]\d\d|2[0-4]\d|25[0-5])\.(\d|\d\d|[0-1]\d\d|2[0-4]\d|25[0-5])\.(\d|\d\d|[0-1]\d\d|2[0-4]\d|25[0-5])\.(\d|\d\d|[0-1]\d\d|2[0-4]\d|25[0-5]))$</Expression>
    <NamesToMatch>TCP,IP</NamesToMatch>
    <Message>The format for {0} is invalid</Message>
  </RegularExpressions>
  <RegularExpressions>
    <ID>8</ID>
    <Description>UNC</Description>
    <Expression>^\\{2}[\w-]+\\(([\w-][\w-\s]*[\w-]+[$$]?$)|([\w-][$$]?$))</Expression>
    <NamesToMatch>UNC</NamesToMatch>
    <Message>The format for {0} is invalid</Message>
  </RegularExpressions>
  <RegularExpressions>
    <ID>9</ID>
    <Description>File Names</Description>
    <Expression>^([a-zA-Z]\:)(\\[^\\/:*?&lt;&gt;"|]*(?&lt;![ ]))*(\.[a-zA-Z]{2,6})$</Expression>
    <NamesToMatch>File,FileName</NamesToMatch>
    <Message>The format for {0} is invalid</Message>
  </RegularExpressions>
  <RegularExpressions>
    <ID>10</ID>
    <Description>US Dollar Amounts</Description>
    <Expression>^(\$)?(([1-9]\d{0,2}(\,\d{3})*)|([1-9]\d*)|(0))(\.\d{2})?$</Expression>
    <NamesToMatch>Dollar,Currency</NamesToMatch>
    <Message>The format for {0} is invalid</Message>
  </RegularExpressions>
  <RegularExpressions>
    <ID>11</ID>
    <Description>Russion Postal Code</Description>
    <Expression>^[0-9]{6}</Expression>
    <NamesToMatch>PostalCode</NamesToMatch>
    <Message>The format for {0} is invalid</Message>
  </RegularExpressions>
  <RegularExpressions>
    <ID>12</ID>
    <Description>Dutch Postal Codes</Description>
    <Expression>^[1-9][0-9]{3}\s?[a-zA-Z]{2}$</Expression>
    <NamesToMatch>PostalCode</NamesToMatch>
    <Message>The format for {0} is invalid</Message>
  </RegularExpressions>
  <RegularExpressions>
    <ID>13</ID>
    <Description>Canadian Postal Codes</Description>
    <Expression>^[a-zA-Z]{1}[0-9]{1}[a-zA-Z]{1}(\-| |){1}[0-9]{1}[a-zA-Z]{1}[0-9]{1}$</Expression>
    <NamesToMatch>PostalCode</NamesToMatch>
    <Message>The format for {0} is invalid</Message>
  </RegularExpressions>
  <RegularExpressions>
    <ID>14</ID>
    <Description>Visa/MasterCard,AMEX Validator</Description>
    <Expression>^((4\d{3})|(5[1-5]\d{2}))(-?|\040?)(\d{4}(-?|\040?)){3}|^(3[4,7]\d{2})(-?|\040?)\d{6}(-?|\040?)\d{5}</Expression>
    <NamesToMatch>CreditCard,CC</NamesToMatch>
    <Message>The format for {0} is invalid</Message>
  </RegularExpressions>
</RegularExpression>